<?xml version="1.0" encoding="UTF-8"?>
<beans xmlns="http://www.springframework.org/schema/beans"
       xmlns:xsi="http://www.w3.org/2001/XMLSchema-instance"
       xmlns:dubbo="http://code.alibabatech.com/schema/dubbo"
       xsi:schemaLocation="http://www.springframework.org/schema/beans http://www.springframework.org/schema/beans/spring-beans.xsd
		http://code.alibabatech.com/schema/dubbo http://code.alibabatech.com/schema/dubbo/dubbo.xsd">

    <!-- 4. zipkin 相关的配置 -->
    <bean id="sender" class="zipkin2.reporter.beans.OkHttpSenderFactoryBean">
        <property name="endpoint" value="http://localhost:8086/api/v2/spans"/>
    </bean>

    <bean id="tracing" class="brave.spring.beans.TracingFactoryBean">
        <property name="localServiceName" value="cloud-collection-web"/>
        <property name="spanReporter">
            <bean class="zipkin2.reporter.beans.AsyncReporterFactoryBean">
                <property name="sender" ref="sender"/>
                <!-- wait up to half a second for any in-flight spans on close -->
                <property name="closeTimeout" value="500"/>
            </bean>
        </property>
        <property name="currentTraceContext">
            <bean class="brave.spring.beans.CurrentTraceContextFactoryBean">
                <property name="scopeDecorators">
                    <bean class="brave.context.slf4j.MDCScopeDecorator" factory-method="create"/>
                </property>
            </bean>
        </property>
    </bean>

</beans>
